{
  "isUpdateAvailable": true,
  "partsToUpdate": ["cards", "events"],
  "cards": [
    {
      "name": "Agatha Harkness",
      "cost": "6",
      "power": "12",
      "ability": "Game Start: Draw Agatha. She controls your cards on even turns.",
      "released": true,
      "series": "3",
      "type": "character",
      "tags": ["game start"],
      "code": "AgthHrknssE",
      "id": 7
    },
    {
      "name": "Alioth",
      "cost": "6",
      "power": "9",
      "ability": "On Reveal: Remove the text from all unrevealed enemy characters here.",
      "released": true,
      "series": "5",
      "type": "character",
      "tags": ["on reveal", "remove"],
      "code": "Alth6",
      "id": 13
    },
    {
      "name": "Colleen Wing",
      "cost": "2",
      "power": "3",
      "ability": "On Reveal: Discard the card that costs the least from your hand.",
      "released": true,
      "series": "3",
      "type": "character",
      "tags": ["on reveal", "discard"],
      "code": "CllnWngB",
      "id": 65
    },
    {
      "name": "Cosmo",
      "cost": "3",
      "power": "3",
      "ability": "Ongoing: On Reveal abilities won't happen here.",
      "released": true,
      "series": "1",
      "type": "character",
      "tags": ["ongoing"],
      "code": "Csm5",
      "id": 69
    },
    {
      "name": "Destroyer",
      "cost": "6",
      "power": "18",
      "ability": "On Reveal: Destroy your other cards.",
      "released": true,
      "series": "3",
      "type": "character",
      "tags": ["on reveal", "destroy"],
      "code": "Dstrr9",
      "id": 84
    },
    {
      "name": "Enchantress",
      "cost": "5",
      "power": "8",
      "ability": "On Reveal: Remove the abilities from all Ongoing cards here.",
      "released": true,
      "series": "1",
      "type": "character",
      "tags": ["on reveal", "remove"],
      "code": "EnchntrssB",
      "id": 107
    },
    {
      "name": "Killmonger",
      "cost": "3",
      "power": "3",
      "ability": "On Reveal: Destroy ALL 1-Cost cards.",
      "released": true,
      "series": "2",
      "type": "character",
      "tags": ["on reveal", "destroy"],
      "code": "KllmngrA",
      "id": 184
    },
    {
      "name": "Lockjaw",
      "cost": "2",
      "power": "3",
      "ability": "Activate: After you play your next card, swap it with a card in your deck.",
      "released": true,
      "series": "3",
      "type": "character",
      "tags": ["activate"],
      "code": "Lckjw7",
      "id": 200
    },
    {
      "name": "Mystique",
      "cost": "3",
      "power": "1",
      "ability": "On Reveal: If the last card you played has an Ongoing, copy its text. <i>(if it's in play)</i>",
      "released": true,
      "series": "3",
      "type": "character",
      "tags": ["on reveal", "ongoing"],
      "code": "Mstq8",
      "id": 246
    },
    {
      "name": "Negasonic Teenage Warhead",
      "cost": "4",
      "power": "5",
      "ability": "After an enemy character is played here, destroy it. <i>(once per game)</i>",
      "released": true,
      "series": "3",
      "type": "character",
      "tags": ["destroy"],
      "code": "NgsncTngWrhd17",
      "id": 251
    },
    {
      "name": "Red Guardian",
      "cost": "3",
      "power": "2",
      "ability": "On Reveal: Afflict the lowest-Power enemy card here with -2 Power and remove its text.",
      "released": true,
      "series": "5",
      "type": "character",
      "tags": ["on reveal", "afflict", "remove"],
      "code": "RdGrdnB",
      "id": 293
    },
    {
      "name": "Shadow King",
      "cost": "2",
      "power": "2",
      "ability": "On Reveal: Reset all cards here to their original Power.",
      "released": true,
      "series": "3",
      "type": "character",
      "tags": ["on reveal"],
      "code": "ShdwKngA",
      "id": 322
    },
    {
      "name": "Shang-Chi",
      "cost": "4",
      "power": "3",
      "ability": "On Reveal: Destroy an enemy card here that has 10 or more Power.",
      "released": true,
      "series": "2",
      "type": "character",
      "tags": ["on reveal", "destroy"],
      "code": "ShngCh8",
      "id": 323
    },
    {
      "name": "Kang",
      "cost": "3",
      "power": "4",
      "ability": "Game Start: Replace this with 4 Kangs with text from random cards that Cost 3 or more.",
      "released": true,
      "series": "5",
      "type": "character",
      "tags": ["game start"],
      "code": "Kng4",
      "id": 178
    },
    {
      "name": "Dormammu",
      "cost": "7",
      "power": "12",
      "ability": "Game Start: Begin a <mark>Summoning Ritual</mark>. <i>(Add step 1 to hand.)</i>",
      "released": true,
      "series": "5",
      "type": "character",
      "tags": ["game start"],
      "code": "Drmmm8",
      "id": 434,
      "refs": [435, 436, 437]
    },
    {
      "name": "Stardust",
      "cost": "4",
      "power": "6",
      "ability": "Ongoing: Cards can’t be added to locations except by playing or moving them.",
      "released": true,
      "series": "5",
      "type": "character",
      "tags": ["ongoing", "move"],
      "code": "Strdst8",
      "id": 466
    },
    {
      "name": "Awesome Andy",
      "cost": "2",
      "power": "2",
      "ability": "Activate: Give one of your cards at each other location +2 Power.",
      "released": true,
      "series": "4",
      "type": "character",
      "tags": ["activate"],
      "code": "AwsmAndB",
      "id": 473
    },
    {
      "name": "Viv Vision",
      "cost": "3",
      "power": "3",
      "ability": "At the start of each turn, give all cards in your hand +1 Power if you’re winning here. Otherwise, move this to another location.",
      "released": true,
      "series": "Season Pass",
      "type": "character",
      "tags": ["move"],
      "code": "Vv3",
      "id": 406
    },
    {
      "name": "Man-Spider",
      "cost": "5",
      "power": "1",
      "ability": "On Reveal: Merge the last card you played into this. When this merges, double its Power.",
      "released": false,
      "series": "NA",
      "type": "character",
      "tags": ["on reveal"],
      "code": "MnSpdr9",
      "id": 491
    },
    {
      "name": "Spider-Man Noir",
      "cost": "4",
      "power": "4",
      "ability": "On Reveal: If your other cards in play cost exactly 8 total, add the top card of your deck here. Set its Power to 8.",
      "released": false,
      "series": "NA",
      "type": "character",
      "tags": ["on reveal"],
      "code": "SpdrMnNrD",
      "id": 492
    },
    {
      "name": "Remote Mines",
      "cost": "1",
      "power": "0",
      "ability": "On Reveal: Afflict the 2 highest-Power enemy cards here with -2 Power.",
      "released": false,
      "series": "NA",
      "type": "skill",
      "tags": ["on reveal", "afflict"],
      "code": "",
      "id": 493
    },
    {
      "name": "Web Sling",
      "cost": "1",
      "power": "0",
      "ability": "On Reveal: Next turn, you can move one of your cards away from here.",
      "released": false,
      "series": "NA",
      "type": "skill",
      "tags": ["on reveal", "move"],
      "code": "WbSlng8",
      "id": 494
    },
    {
      "name": "Vibro-Shock Gauntlets",
      "cost": "1",
      "power": "0",
      "ability": "On Reveal: Give your highest-Power card here +2 Power. You get +1 Energy next turn.",
      "released": false,
      "series": "NA",
      "type": "skill",
      "tags": ["on reveal"],
      "code": "",
      "id": 495
    },
    {
      "name": "Deafening Chord",
      "cost": "1",
      "power": "0",
      "ability": "On Reveal: Afflict an enemy character here that costs 3 or less with -1 Power and remove its text.",
      "released": false,
      "series": "NA",
      "type": "skill",
      "tags": ["on reveal", "afflict", "remove"],
      "code": "DfnngChrdE",
      "id": 496
    },
    {
      "name": "Flight Harness",
      "cost": "1",
      "power": "0",
      "ability": "On Reveal: Give your highest-Power card here +1 Power and move it to the right.",
      "released": false,
      "series": "NA",
      "type": "skill",
      "tags": ["on reveal", "move"],
      "code": "",
      "id": 497
    },
    {
      "name": "Hydro-Man",
      "cost": "5",
      "power": "8",
      "ability": "On Reveal: Set the Cost of EACH deck's top card to 1.",
      "released": false,
      "series": "NA",
      "type": "character",
      "tags": ["on reveal"],
      "code": "HdrMn8",
      "id": 498
    },
    {
      "name": "Superior Spider-Man",
      "cost": "3",
      "power": "4",
      "ability": "End of Turn: If you have a card with increased Power in play, you get +1 Energy next turn.",
      "released": false,
      "series": "NA",
      "type": "character",
      "tags": ["end of turn"],
      "code": "SprrSpdrMn11",
      "id": 499
    },
    {
      "name": "Prowler",
      "cost": "3",
      "power": "4",
      "ability": "On Reveal: Add 2 Thief’s Tools to your hand. Set their Costs to 0 if a card moved last turn.",
      "released": false,
      "series": "NA",
      "type": "character",
      "tags": ["on reveal", "move"],
      "code": "Prwlr7",
      "id": 500
    },
    {
      "name": "Spider-Punk",
      "cost": "3",
      "power": "2",
      "ability": "You can move this once. When this moves to a location, steal 2 Power from the highest-Power enemy there.",
      "released": false,
      "series": "NA",
      "type": "character",
      "tags": ["move", "steal"],
      "code": "SpdrPnkA",
      "id": 501
    },
    {
      "name": "Ezekiel Sims",
      "cost": "2",
      "power": "2",
      "ability": "After you play a card with higher Power here, give this +2 Power and move this to another location.",
      "released": false,
      "series": "NA",
      "type": "character",
      "tags": ["move"],
      "code": "EzklSmsB",
      "id": 502
    },
    {
      "name": "Chameleon",
      "cost": "3",
      "power": "3",
      "ability": "On Reveal: Copy the text of another card you revealed here this turn.",
      "released": false,
      "series": "NA",
      "type": "character",
      "tags": ["on reveal"],
      "noArt": true,
      "code": "Chmln9",
      "id": 503
    }
  ],
  "locations": [],
  "seasonInfo": [],
  "seasonStyles": [],
  "seasonEvents": [
    {
      "title": "Daily Login",
      "items": [
        {
          "date": "Sep 3 - Sep 11",
          "items": [
            "Title - Solar-Powered",
            "100 Credits",
            "65 Random Boosters",
            "155 Random Boosters",
            "150 Credits",
            "Mystery Border",
            "Mystery Variant"
          ]
        },
        {
          "date": "Sep 17 - Oct 3",
          "items": [
            "100 Credits",
            "65 Random Boosters",
            "Title - 1% Battery",
            "Rainbow Refraction Border",
            "65 Random Boosters",
            "100 Credits",
            "Premium Mystery Variant",
            "Rainbow Refraction Border",
            "155 Random Boosters",
            "100 Credits",
            "Mystery Variant",
            "Rainbow Refraction Border",
            "100 Credits",
            "Series 4 Collector's Pack"
          ]
        }
      ]
    },
    {
      "title": "Balance Updates",
      "items": [
        {
          "date": "Sep 11",
          "type": "OTA",
          "items": [
            {
              "name": "Shang-Chi",
              "changes": [
                "4/3 – On Reveal: Destroy all enemy cards here that have 10 or more Power.",
                "4/2 – On Reveal: Destroy an enemy card here that has 10 or more Power."
              ]
            },
            {
              "name": "Killmonger",
              "changes": [
                "3/3 – On Reveal: Destroy ALL 1-Cost cards.",
                "3/3 – On Reveal: Destroy ALL 1-Cost cards here."
              ]
            },
            {
              "name": "Enchantress",
              "changes": [
                "4/6 – On Reveal: Remove the abilities from all Ongoing cards here.",
                "4/6 -> 5/8"
              ]
            },
            {
              "name": "Shadow King",
              "changes": [
                "2/2 On Reveal: Set all cards here to their original base Power.",
                "2/2 -> 3/3"
              ]
            },
            {
              "name": "Negasonic Teenage Warhead",
              "changes": [
                "3/3 – After an enemy character is played here, destroy it. (once per game)",
                "3/3 -> 4/5"
              ]
            },
            {
              "name": "Alioth",
              "changes": [
                "6/9 – On Reveal: Remove the text from all unrevealed enemy characters here.",
                "6/9 -> 6/6"
              ]
            },
            {
              "name": "Red Guardian",
              "changes": [
                "3/2 – On Reveal: Afflict the lowest-Power enemy card here with -2 Power and remove its text.",
                "3/2 -> 3/0"
              ]
            },
            {
              "name": "Cosmo",
              "changes": [
                "3/3 – Ongoing: On Reveal abilities won’t happen here.",
                "3/3 -> 4/6"
              ]
            }
          ]
        },
        {
          "date": "Sep 16",
          "type": "Patch",
          "items": [
            {
              "name": "Kang",
              "changes": [
                "5/0 – On Reveal: Look at what your opponent did, then restart the turn. (without this)",
                "3/4 – Game Start: Replace this with 4 Kangs with text from random cards that Cost 3 or more."
              ]
            }
          ]
        },
        {
          "date": "Sep 25",
          "type": "OTA",
          "items": [
            {
              "name": "Killmonger",
              "changes": [
                "3/3 – On Reveal: Destroy ALL 1-Cost cards here.",
                "3/3 – On Reveal: Destroy ALL 1-Cost cards."
              ]
            },
            {
              "name": "Cosmo",
              "changes": [
                "4/6 – Ongoing: On Reveal abilities won't happen here.",
                "4/6 -> 3/3"
              ]
            },
            {
              "name": "Shadow King",
              "changes": [
                "3/3 – On Reveal: Reset all cards here to their original Power.",
                "3/3 -> 2/2"
              ]
            },
            {
              "name": "Alioth",
              "changes": [
                "6/6 – On Reveal: Remove the text from all unrevealed enemy characters here.",
                "6/6 -> 6/9"
              ]
            },
            {
              "name": "Red Guardian",
              "changes": [
                "3/0 – On Reveal: Afflict the lowest-Power enemy card here with -2 Power and remove its text.",
                "3/0 -> 3/2"
              ]
            },
            {
              "name": "Shang-Chi",
              "changes": [
                "4/2 – On Reveal: Destroy an enemy card here that has 10 or more Power.",
                "4/2 -> 4/3"
              ]
            },
            {
              "name": "Colleen Wing",
              "changes": [
                "2/4 – On Reveal: Discard the card that costs the least from your hand.",
                "2/4 -> 2/3"
              ]
            },
            {
              "name": "Agatha Harkness",
              "changes": [
                "6/14 – Game Start: Draw Agatha. She controls your cards on even turns.",
                "6/14 -> 6/12"
              ]
            },
            {
              "name": "Stardust",
              "changes": [
                "4/7 – Ongoing: Cards can’t be added to locations except by playing or moving them.",
                "4/7 -> 4/6"
              ]
            },
            {
              "name": "Viv Vision",
              "changes": [
                "3/2 – At the start of each turn, give all cards in your hand +1 Power if you’re winning here. Otherwise, move this to another location.",
                "3/2 -> 3/3"
              ]
            },
            {
              "name": "Dormammu",
              "changes": [
                "7/10 – Game Start: Begin a Summoning Ritual. (Add step 1 to hand.)",
                "7/10 -> 7/12"
              ]
            },
            {
              "name": "Destroyer",
              "changes": [
                "6/16 – On Reveal: Destroy your cards at other locations.",
                "6/16 -> 6/18"
              ]
            },
            {
              "name": "Awesome Andy",
              "changes": [
                "2/1 – Activate: Give one of your cards at each other location +2 Power.",
                "2/1 -> 2/2"
              ]
            },
            {
              "name": "Lockjaw",
              "changes": [
                "2/2 – Activate: After you play your next card, swap it with one from your deck.",
                "2/2 -> 2/3"
              ]
            },
            {
              "name": "Mystique",
              "changes": [
                "3/0 – On Reveal: If the last card you played has an Ongoing, copy its text. (if able)",
                "3/0 -> 3/1"
              ]
            }
          ]
        }
      ]
    }
  ]
}
